{"id": 1172150051558350853, "bot_name": "Scrambled Literature", "twitter_username": "@SouthernOracle4", "text": "\"Well, sir,\" cried Caderousse, almost breathless with eager admiration, \"you say you loved Valentine, that you were engaged to M.d'\u00c9pinay, for he came this morning to Paris.\" ", "passages": [{"item": 0, "fragment": "Well , sir , ''", "source_name": "Count Of Monte Cristo", "source_position": 128368, "prefix": [400, 25, 523, 25], "full_quote": "\"<used>Well, sir,\" sa</used>id Morrel, sinking into a chair, \"you have heard all, and I have nothing further to tell you.\""}, {"item": 1, "fragment": ", sir , '' cried Caderousse", "source_name": "Count Of Monte Cristo", "source_position": 119951, "prefix": [25, 523, 25, 2], "full_quote": "\"Oh, you are a man of God, <used>sir,\" cried Caderousse</used>; \"for no one knew that Edmond had given you this diamond, and you might have kept it.\""}, {"item": 2, "fragment": "sir , '' cried Caderousse ,", "source_name": "Count Of Monte Cristo", "source_position": 431322, "prefix": [523, 25, 2, 150], "full_quote": "\"Ah, reverend <used>sir,\" cried Caderousse, c</used>lasping his hands, and drawing nearer to Monte Cristo, \"I may indeed say you are my deliverer!\""}, {"item": 3, "fragment": ", '' cried Caderousse , almost breathless with eager admiration , `` you say", "source_name": "Count Of Monte Cristo", "source_position": 110954, "prefix": [25, 2, 150, 161], "full_quote": "\"And that diamo<used>nd,\" cried Caderousse, almost breathless with eager admiration, \"you say</used>, is worth fifty thousand francs?\""}, {"item": 4, "fragment": ", `` you say you loved Valentine , that you were", "source_name": "Count Of Monte Cristo", "source_position": 509110, "prefix": [25, 3, 49, 294], "full_quote": "\"Sir,\" said he to Maximil<used>ian, \"you say you loved Valentine, that you were</used> betrothed to her\""}, {"item": 5, "fragment": "Valentine , that you were engaged to M. d'\u00c9pinay ,", "source_name": "Count Of Monte Cristo", "source_position": 269438, "prefix": [496, 25, 7, 49], "full_quote": "You told me, my dear <used>Valentine, that you were engaged to M.d'\u00c9pinay, a</used>nd that your father was resolved upon completing the match, and that from his will there was no appeal, as M. de Villefort was never known to change a determination once formed"}, {"item": 6, "fragment": "engaged to M. d'\u00c9pinay , for he came this morning to Paris .", "source_name": "Count Of Monte Cristo", "source_position": 369507, "prefix": [3475, 89, 658, 601], "full_quote": "But, since you say nothing remains but for M.d'\u00c9pinay to arrive that the contract may be signed, and the following day you will be his, tomorrow you will be <used>engaged to M.d'\u00c9pinay, for he came this morning to Paris</used>."}]}